asyncgraphs/__init__.py
asyncgraphs/construction.py
asyncgraphs/execution.py
asyncgraphs/py.typed
asyncgraphs-0.0.4.dist-info/METADATA
asyncgraphs-0.0.4.dist-info/WHEEL
asyncgraphs-0.0.4.dist-info/licenses/LICENSE
asyncgraphs-0.0.4.dist-info/RECORD
