Metadata-Version: 2.1
Name: asyncgraphs
Version: 0.0.4
Project-URL: Source, https://github.com/SamVermeulen42/asyncgraphs
Project-URL: Documentation, https://samvermeulen42.github.io/asyncgraphs/
Author-email: Sam Vermeulen <sam.verm@yahoo.com>
License-Expression: MIT
License-File: LICENSE
Classifier: Development Status :: 2 - Pre-Alpha
Classifier: Programming Language :: Python
Classifier: Programming Language :: Python :: 3
Classifier: Programming Language :: Python :: 3 :: Only
Classifier: Programming Language :: Python :: 3.10
Classifier: Programming Language :: Python :: 3.11
Classifier: Typing :: Typed
Requires-Python: >=3.10
Requires-Dist: sentinel<1.1.0,>=1.0.0
Provides-Extra: dev
Requires-Dist: black==23.1.0; extra == 'dev'
Requires-Dist: coverage<8.0,>=7.1.0; extra == 'dev'
Requires-Dist: isort==5.12.0; extra == 'dev'
Requires-Dist: mypy==1.0.1; extra == 'dev'
Requires-Dist: pytest-asyncio<0.21.0,>=0.20.0; extra == 'dev'
Requires-Dist: pytest<8.0.0,>=7.2.1; extra == 'dev'
Requires-Dist: ruff==0.0.247; extra == 'dev'
Provides-Extra: docs
Requires-Dist: mkdocs-material<10.0.0,>=9.0.15; extra == 'docs'
Requires-Dist: mkdocs<2.0.0,>=1.4.2; extra == 'docs'
